{"errors":[],"warnings":[],"namedChunkGroups":{"app":{"chunks":[15,11,4],"assets":["webpack-runtime-89f346358f7ae4c5e9a1.js","webpack-runtime-89f346358f7ae4c5e9a1.js.map","framework-f600a0dcdbbe2ab3be17.js","framework-f600a0dcdbbe2ab3be17.js.map","app-ff614d5ea6d95c579d87.js","app-ff614d5ea6d95c579d87.js.map"],"children":{},"childAssets":{}},"component---src-pages-404-js":{"chunks":[3,2,0,1,5],"assets":["styles.b558d5e4ae1cb4510711.css","styles-8d3db5124725dcff78a7.js","styles-8d3db5124725dcff78a7.js.map","de71a805-f366b0f91d20fcfeccb1.js","de71a805-f366b0f91d20fcfeccb1.js.map","5e2a4920-bee54b5f548eb2ed49d9.js","5e2a4920-bee54b5f548eb2ed49d9.js.map","commons-91ce454ea4e3b8435852.js","commons-91ce454ea4e3b8435852.js.map","component---src-pages-404-js-869209446164751a9f5e.js","component---src-pages-404-js-869209446164751a9f5e.js.map"],"children":{},"childAssets":{}},"component---src-pages-about-js":{"chunks":[3,2,0,1,6],"assets":["styles.b558d5e4ae1cb4510711.css","styles-8d3db5124725dcff78a7.js","styles-8d3db5124725dcff78a7.js.map","de71a805-f366b0f91d20fcfeccb1.js","de71a805-f366b0f91d20fcfeccb1.js.map","5e2a4920-bee54b5f548eb2ed49d9.js","5e2a4920-bee54b5f548eb2ed49d9.js.map","commons-91ce454ea4e3b8435852.js","commons-91ce454ea4e3b8435852.js.map","component---src-pages-about-js-f8a45717d6188728e67d.js","component---src-pages-about-js-f8a45717d6188728e67d.js.map"],"children":{},"childAssets":{}},"component---src-pages-blog-js":{"chunks":[3,2,0,1,7],"assets":["styles.b558d5e4ae1cb4510711.css","styles-8d3db5124725dcff78a7.js","styles-8d3db5124725dcff78a7.js.map","de71a805-f366b0f91d20fcfeccb1.js","de71a805-f366b0f91d20fcfeccb1.js.map","5e2a4920-bee54b5f548eb2ed49d9.js","5e2a4920-bee54b5f548eb2ed49d9.js.map","commons-91ce454ea4e3b8435852.js","commons-91ce454ea4e3b8435852.js.map","component---src-pages-blog-js-99aa276397e2a0912100.js","component---src-pages-blog-js-99aa276397e2a0912100.js.map"],"children":{},"childAssets":{}},"component---src-pages-contact-js":{"chunks":[3,2,0,1,8],"assets":["styles.b558d5e4ae1cb4510711.css","styles-8d3db5124725dcff78a7.js","styles-8d3db5124725dcff78a7.js.map","de71a805-f366b0f91d20fcfeccb1.js","de71a805-f366b0f91d20fcfeccb1.js.map","5e2a4920-bee54b5f548eb2ed49d9.js","5e2a4920-bee54b5f548eb2ed49d9.js.map","commons-91ce454ea4e3b8435852.js","commons-91ce454ea4e3b8435852.js.map","component---src-pages-contact-js-ffd29594e64c3e2f24ca.js","component---src-pages-contact-js-ffd29594e64c3e2f24ca.js.map"],"children":{},"childAssets":{}},"component---src-pages-index-js":{"chunks":[3,2,0,1,9],"assets":["styles.b558d5e4ae1cb4510711.css","styles-8d3db5124725dcff78a7.js","styles-8d3db5124725dcff78a7.js.map","de71a805-f366b0f91d20fcfeccb1.js","de71a805-f366b0f91d20fcfeccb1.js.map","5e2a4920-bee54b5f548eb2ed49d9.js","5e2a4920-bee54b5f548eb2ed49d9.js.map","commons-91ce454ea4e3b8435852.js","commons-91ce454ea4e3b8435852.js.map","component---src-pages-index-js-a521642b4c22484fe62f.js","component---src-pages-index-js-a521642b4c22484fe62f.js.map"],"children":{},"childAssets":{}},"component---src-templates-blog-js":{"chunks":[3,2,0,1,10],"assets":["styles.b558d5e4ae1cb4510711.css","styles-8d3db5124725dcff78a7.js","styles-8d3db5124725dcff78a7.js.map","de71a805-f366b0f91d20fcfeccb1.js","de71a805-f366b0f91d20fcfeccb1.js.map","5e2a4920-bee54b5f548eb2ed49d9.js","5e2a4920-bee54b5f548eb2ed49d9.js.map","commons-91ce454ea4e3b8435852.js","commons-91ce454ea4e3b8435852.js.map","component---src-templates-blog-js-a7911f840a19c14407d9.js","component---src-templates-blog-js-a7911f840a19c14407d9.js.map"],"children":{},"childAssets":{}},"polyfills-dom":{"chunks":[14],"assets":["polyfills-dom-f4c7ded5153ddff9f212.js","polyfills-dom-f4c7ded5153ddff9f212.js.map"],"children":{},"childAssets":{}},"polyfills-core-js":{"chunks":[12],"assets":["polyfills-core-js-98a18980d3a158327c96.js","polyfills-core-js-98a18980d3a158327c96.js.map"],"children":{},"childAssets":{}},"polyfills-css-shim":{"chunks":[13],"assets":["polyfills-css-shim-6ec62deb25ed9cc0d2e6.js","polyfills-css-shim-6ec62deb25ed9cc0d2e6.js.map"],"children":{},"childAssets":{}}},"assetsByChunkName":{"app":["webpack-runtime-89f346358f7ae4c5e9a1.js","framework-f600a0dcdbbe2ab3be17.js","app-ff614d5ea6d95c579d87.js"],"component---src-pages-404-js":["styles.b558d5e4ae1cb4510711.css","styles-8d3db5124725dcff78a7.js","de71a805-f366b0f91d20fcfeccb1.js","5e2a4920-bee54b5f548eb2ed49d9.js","commons-91ce454ea4e3b8435852.js","component---src-pages-404-js-869209446164751a9f5e.js"],"component---src-pages-about-js":["styles.b558d5e4ae1cb4510711.css","styles-8d3db5124725dcff78a7.js","de71a805-f366b0f91d20fcfeccb1.js","5e2a4920-bee54b5f548eb2ed49d9.js","commons-91ce454ea4e3b8435852.js","component---src-pages-about-js-f8a45717d6188728e67d.js"],"component---src-pages-blog-js":["styles.b558d5e4ae1cb4510711.css","styles-8d3db5124725dcff78a7.js","de71a805-f366b0f91d20fcfeccb1.js","5e2a4920-bee54b5f548eb2ed49d9.js","commons-91ce454ea4e3b8435852.js","component---src-pages-blog-js-99aa276397e2a0912100.js"],"component---src-pages-contact-js":["styles.b558d5e4ae1cb4510711.css","styles-8d3db5124725dcff78a7.js","de71a805-f366b0f91d20fcfeccb1.js","5e2a4920-bee54b5f548eb2ed49d9.js","commons-91ce454ea4e3b8435852.js","component---src-pages-contact-js-ffd29594e64c3e2f24ca.js"],"component---src-pages-index-js":["styles.b558d5e4ae1cb4510711.css","styles-8d3db5124725dcff78a7.js","de71a805-f366b0f91d20fcfeccb1.js","5e2a4920-bee54b5f548eb2ed49d9.js","commons-91ce454ea4e3b8435852.js","component---src-pages-index-js-a521642b4c22484fe62f.js"],"component---src-templates-blog-js":["styles.b558d5e4ae1cb4510711.css","styles-8d3db5124725dcff78a7.js","de71a805-f366b0f91d20fcfeccb1.js","5e2a4920-bee54b5f548eb2ed49d9.js","commons-91ce454ea4e3b8435852.js","component---src-templates-blog-js-a7911f840a19c14407d9.js"],"polyfills-dom":["polyfills-dom-f4c7ded5153ddff9f212.js"],"polyfills-core-js":["polyfills-core-js-98a18980d3a158327c96.js"],"polyfills-css-shim":["polyfills-css-shim-6ec62deb25ed9cc0d2e6.js"]}}